camper/__init__.py
camper/common.py
camper/constants.py
camper/dummyrv.py
camper/minormode.py
camper/nodes.py
camper/properties.py
camper/session.py
camper/typehint.py
camper-1.0.1.dist-info/LICENSE
camper-1.0.1.dist-info/METADATA
camper-1.0.1.dist-info/WHEEL
camper-1.0.1.dist-info/top_level.txt
camper-1.0.1.dist-info/RECORD
