Metadata-Version: 2.1
Name: camper
Version: 1.0.1
Summary: Pythonic utilities for Tweak RV
Home-page: https://gitlab.com/davinozen/camper
Author: David (Ming) Zeng
Author-email: me@davidvfx.com
License: UNKNOWN
Platform: UNKNOWN
Classifier: Programming Language :: Python :: 3.6
Classifier: License :: OSI Approved :: MIT License
Classifier: Operating System :: OS Independent
Requires-Python: >=3.6
